sigterm.py
graceful_sigterm-0.1.3.dist-info/LICENSE
graceful_sigterm-0.1.3.dist-info/METADATA
graceful_sigterm-0.1.3.dist-info/WHEEL
graceful_sigterm-0.1.3.dist-info/top_level.txt
graceful_sigterm-0.1.3.dist-info/RECORD
