Metadata-Version: 2.1
Name: graceful-sigterm
Version: 0.1.3
Summary: Receive the kill signal from the operating system and gracefully wait for the worker thread to end.
Author: Huang YongSi
Maintainer: Huang YongSi
License: MIT
Keywords: sigterm,kill python
Classifier: Development Status :: 5 - Production/Stable
Classifier: Intended Audience :: Developers
Classifier: Topic :: Software Development :: Libraries :: Python Modules
Classifier: License :: OSI Approved :: MIT License
Classifier: Programming Language :: Python :: 3
Classifier: Programming Language :: Python :: 3 :: Only
License-File: LICENSE
